tidas_tools/__init__.py
tidas_tools/convert.py
tidas_tools/export.py
tidas_tools/tidas_log.py
tidas_tools/validate.py
tidas_tools/validate_methodologies.py
tidas_tools/eilcd/schemas/ILCD_Categories.xsd
tidas_tools/eilcd/schemas/ILCD_Common_DataTypes.xsd
tidas_tools/eilcd/schemas/ILCD_Common_EnumerationValues.xsd
tidas_tools/eilcd/schemas/ILCD_Common_Groups.xsd
tidas_tools/eilcd/schemas/ILCD_Common_Validation.xsd
tidas_tools/eilcd/schemas/ILCD_ContactDataSet.xsd
tidas_tools/eilcd/schemas/ILCD_Documentation.xsd
tidas_tools/eilcd/schemas/ILCD_FlowDataSet.xsd
tidas_tools/eilcd/schemas/ILCD_FlowPropertyDataSet.xsd
tidas_tools/eilcd/schemas/ILCD_ILCD.xsd
tidas_tools/eilcd/schemas/ILCD_LCIAMethodDataSet.xsd
tidas_tools/eilcd/schemas/ILCD_LCIAMethodologies.xsd
tidas_tools/eilcd/schemas/ILCD_LifeCycleModelDataSet.xsd
tidas_tools/eilcd/schemas/ILCD_Locations.xsd
tidas_tools/eilcd/schemas/ILCD_ProcessDataSet.xsd
tidas_tools/eilcd/schemas/ILCD_SourceDataSet.xsd
tidas_tools/eilcd/schemas/ILCD_UnitGroupDataSet.xsd
tidas_tools/eilcd/schemas/xml.xsd
tidas_tools/eilcd/stylesheets/ILCDClassification_Reference.xml
tidas_tools/eilcd/stylesheets/ILCDFlowCategorization_Reference.xml
tidas_tools/eilcd/stylesheets/ILCDLCIAMethodologies_Reference.xml
tidas_tools/eilcd/stylesheets/ILCDLocations_Reference.xml
tidas_tools/eilcd/stylesheets/common.xsl
tidas_tools/eilcd/stylesheets/compliance_1.1.xsl
tidas_tools/eilcd/stylesheets/contact2html.xsl
tidas_tools/eilcd/stylesheets/dataset-common.xsl
tidas_tools/eilcd/stylesheets/display-common.xsl
tidas_tools/eilcd/stylesheets/flow2html.xsl
tidas_tools/eilcd/stylesheets/flowproperty2html.xsl
tidas_tools/eilcd/stylesheets/ilcd2xls.xsl
tidas_tools/eilcd/stylesheets/lciamethod2html.xsl
tidas_tools/eilcd/stylesheets/process2html.xsl
tidas_tools/eilcd/stylesheets/reference_types.xml
tidas_tools/eilcd/stylesheets/source2html.xsl
tidas_tools/eilcd/stylesheets/unitTests.xsl
tidas_tools/eilcd/stylesheets/unitgroup2html.xsl
tidas_tools-0.0.21.dist-info/METADATA
tidas_tools-0.0.21.dist-info/WHEEL
tidas_tools-0.0.21.dist-info/entry_points.txt
tidas_tools-0.0.21.dist-info/top_level.txt
tidas_tools-0.0.21.dist-info/RECORD
