Metadata-Version: 2.4
Name: tidas-tools
Version: 0.0.21
Summary: tidas-tools
Author-email: Nan LI <linanenv@gmail.com>
Requires-Python: <4.0,>=3.9
Requires-Dist: boto3>=1.40.62
Requires-Dist: jsonschema>=4.25.1
Requires-Dist: psycopg2-binary>=2.9.11
Requires-Dist: python-dotenv>=1.2.1
Requires-Dist: referencing<0.37.0,>=0.36.2
Requires-Dist: tqdm>=4.67.1
Requires-Dist: xmltodict>=1.0.2
Requires-Dist: PyYAML>=6.0.3
